crystalwindow/FileHelper.py
crystalwindow/Fonts.py
crystalwindow/System.py
crystalwindow/__init__.py
crystalwindow/ai.py
crystalwindow/animation.py
crystalwindow/apphelper.py
crystalwindow/assets.py
crystalwindow/camera.py
crystalwindow/chatvpn.py
crystalwindow/clock.py
crystalwindow/collision.py
crystalwindow/color_handler.py
crystalwindow/crystal3d.py
crystalwindow/draw_helpers.py
crystalwindow/draw_rects.py
crystalwindow/draw_text_helper.py
crystalwindow/draw_tool.py
crystalwindow/fun_helpers.py
crystalwindow/gravity.py
crystalwindow/gui.py
crystalwindow/gui_ext.py
crystalwindow/math.py
crystalwindow/messagebus.py
crystalwindow/objects.py
crystalwindow/scores.py
crystalwindow/sprites.py
crystalwindow/tilemap.py
crystalwindow/ver_warner.py
crystalwindow/websearch.py
crystalwindow/window.py
crystalwindow/Icons/default_icon.png
crystalwindow/Icons/file_icons.png
crystalwindow/gametests/3dsquare.py
crystalwindow/gametests/__init__.py
crystalwindow/gametests/__main__.py
crystalwindow/gametests/gravitytest.py
crystalwindow/gametests/guitesting.py
crystalwindow/gametests/sandbox.py
crystalwindow/gametests/squaremove.py
crystalwindow/gametests/testtttagain.py
crystalwindow/gametests/windowtesting.py
crystalwindow-5.9.dist-info/licenses/LICENSE
crystalwindow-5.9.dist-info/METADATA
crystalwindow-5.9.dist-info/WHEEL
crystalwindow-5.9.dist-info/top_level.txt
crystalwindow-5.9.dist-info/RECORD
