Metadata-Version: 2.4
Name: crystalwindow
Version: 5.9
Summary: A Tkinter powered window + GUI toolkit made by Crystal (ME)! Easier apps, smoother UI and all-in-one helpers!, Gui, Buttons, FileHelper, Sprites, Animations, Colors, Math, Gravity, Camera, 3D and more!
Home-page: https://pypi.org/project/crystalwindow/
Author: CrystalBallyHereXD
Author-email: mavilla.519@gmail.com
Project-URL: Homepage, https://github.com/yourusername/crystalwindow
Project-URL: YouTube, https://www.Youtube.com/@CrystalBallyHereXD
Project-URL: PiWheels, https://www.piwheels.org/project/crystalwindow/
Keywords: tkinter gui window toolkit easy crystalwindow crystal cw player moveable easygui python py file math gravity hex color
Classifier: Programming Language :: Python :: 3
Classifier: Operating System :: OS Independent
Classifier: Topic :: Software Development :: User Interfaces
Classifier: License :: OSI Approved :: MIT License
Requires-Python: >=3.6
License-File: LICENSE
Requires-Dist: requests
Requires-Dist: packaging
Requires-Dist: pillow
Dynamic: author
Dynamic: author-email
Dynamic: classifier
Dynamic: description
Dynamic: description-content-type
Dynamic: home-page
Dynamic: keywords
Dynamic: license-file
Dynamic: project-url
Dynamic: requires-dist
Dynamic: requires-python
Dynamic: summary
